ordotools/__init__.py
ordotools/sanctoral/__init__.py
ordotools/sanctoral/country/_TEMPLATE.py
ordotools/sanctoral/country/__init__.py
ordotools/sanctoral/country/australiae.py
ordotools/sanctoral/country/hispaniae.py
ordotools/sanctoral/country/nameofcountry.py
ordotools/sanctoral/diocese/_TEMPLATE.py
ordotools/sanctoral/diocese/__init__.py
ordotools/sanctoral/diocese/bathurstensis.py
ordotools/sanctoral/diocese/lismorensis.py
ordotools/sanctoral/diocese/maitlandensis.py
ordotools/sanctoral/diocese/melbournensis.py
ordotools/sanctoral/diocese/nameofdiocese.py
ordotools/sanctoral/diocese/rennes.py
ordotools/sanctoral/diocese/rockhamptonensis.py
ordotools/sanctoral/diocese/roman.py
ordotools/tools/__init__.py
ordotools/tools/algorithm.py
ordotools/tools/commemorations.py
ordotools/tools/fasting.py
ordotools/tools/feast.py
ordotools/tools/helpers.py
ordotools/tools/liturgical_dates.py
ordotools/tools/logger.py
ordotools/tools/parts.py
ordotools/tools/rank.py
ordotools/tools/temporal.py
ordotools/tools/temporal_data.py
ordotools/tools/translations.py
ordotools-0.0.43.dist-info/COPYING
ordotools-0.0.43.dist-info/METADATA
ordotools-0.0.43.dist-info/WHEEL
ordotools-0.0.43.dist-info/top_level.txt
ordotools-0.0.43.dist-info/RECORD
