Metadata-Version: 2.1
Name: ordotools
Version: 0.0.43
Summary: A set of tools for producing a traditional Catholic Ordo, given a year and diocese
Author: corei8 (Fr. G.R.Barnes)
Author-email: corei8.github@gmail.com
Classifier: Programming Language :: Python :: 3
License-File: COPYING
Requires-Dist: python-dateutil
